SocValidator/Setup.py
SocValidator/SocValidator.py
SocValidator/SocValidatorGUI.py
DummyValidator-0.0.0.1.dist-info/METADATA
DummyValidator-0.0.0.1.dist-info/WHEEL
DummyValidator-0.0.0.1.dist-info/top_level.txt
DummyValidator-0.0.0.1.dist-info/RECORD
